my_package_jenson_2/__init__.py
my_package_jenson_2/module1.py
my_package_jenson_2/module2.py
my_package_jenson_2-0.0.1.dist-info/METADATA
my_package_jenson_2-0.0.1.dist-info/WHEEL
my_package_jenson_2-0.0.1.dist-info/top_level.txt
my_package_jenson_2-0.0.1.dist-info/RECORD
