Metadata-Version: 2.1
Name: my_package_jenson_2
Version: 0.0.1
Summary: My First Python Package
Author: JENSON
